etcd_distro/__init__.py
etcd_distro/_program.py
etcd_distro/etcd/__init__.py
etcd_distro/etcd/__main__.py
etcd_distro/etcdbin/__init__.py
etcd_distro/etcdbin/etcd
etcd_distro/etcdbin/etcdctl
etcd_distro/etcdbin/etcdutl
etcd_distro/etcdctl/__init__.py
etcd_distro/etcdctl/__main__.py
etcd_distro/etcdutl/__init__.py
etcd_distro/etcdutl/__main__.py
etcd_distro-3.5.1.dist-info/LICENSE
etcd_distro-3.5.1.dist-info/METADATA
etcd_distro-3.5.1.dist-info/WHEEL
etcd_distro-3.5.1.dist-info/entry_points.txt
etcd_distro-3.5.1.dist-info/top_level.txt
etcd_distro-3.5.1.dist-info/RECORD
